pytmhi/__init__.py
pytmhi-1.1.1.dist-info/licenses/LICENSE.md
pytmhi-1.1.1.dist-info/METADATA
pytmhi-1.1.1.dist-info/WHEEL
pytmhi-1.1.1.dist-info/top_level.txt
pytmhi-1.1.1.dist-info/RECORD
