Metadata-Version: 2.4
Name: pytmhi
Version: 1.1.1
Summary: A py package to access the T-Mobile Home Internet API
Author-email: "Ed Leckert,Michael R. Torres" <ed@edleckertimages.com>
Project-URL: Homepage, https://github.com/EdLeckert/py-tmhi.git
Project-URL: Issues, https://github.com/EdLeckert/py-tmhi/issues
Classifier: Programming Language :: Python :: 3
Classifier: Operating System :: OS Independent
Requires-Python: >=3.8
License-File: LICENSE.md
Dynamic: license-file
